{
  "publicPath": "/_nuxt/",
  "all": [
    "../server/index.spa.html",
    "11a654f520784684b6aa.js",
    "17e699498305c7ff6df5.js",
    "26d5db59123458392e2c.js",
    "3815ef41efb6895f3788.js",
    "433211e6c71f28873e71.js",
    "487b94672ebf506a4b2d.js",
    "51270e3b36c76d4e5a07.js",
    "64d07703f4267d1456dd.js",
    "659121f4f3bec0c1b84a.js",
    "8ac408db1f8de67c8087.js",
    "97646f7ee231e3480e82.js",
    "LICENSES",
    "b60edd0b7a1f0544497c.js",
    "c7382fcef0a74136ba08.js",
    "da0de3a983393419fc24.js",
    "e9235617c50fe3499061.js"
  ],
  "initial": [
    "c7382fcef0a74136ba08.js",
    "64d07703f4267d1456dd.js",
    "17e699498305c7ff6df5.js",
    "da0de3a983393419fc24.js"
  ],
  "async": [
    "11a654f520784684b6aa.js",
    "26d5db59123458392e2c.js",
    "3815ef41efb6895f3788.js",
    "433211e6c71f28873e71.js",
    "487b94672ebf506a4b2d.js",
    "51270e3b36c76d4e5a07.js",
    "659121f4f3bec0c1b84a.js",
    "8ac408db1f8de67c8087.js",
    "97646f7ee231e3480e82.js",
    "b60edd0b7a1f0544497c.js",
    "e9235617c50fe3499061.js"
  ],
  "modules": {
    "12662112": [
      2
    ],
    "13132126": [
      2
    ],
    "26080739": [
      16
    ],
    "27045676": [
      3
    ],
    "27582039": [
      11
    ],
    "28904952": [
      15
    ],
    "40087803": [
      2
    ],
    "41510207": [
      8
    ],
    "43690296": [
      11
    ],
    "45420744": [
      10
    ],
    "50745460": [
      2
    ],
    "52055296": [
      8
    ],
    "59514712": [
      2
    ],
    "62761450": [
      6
    ],
    "63591630": [
      2
    ],
    "63781170": [
      1
    ],
    "64907094": [
      2
    ],
    "67242669": [
      2
    ],
    "69661489": [
      2
    ],
    "70188907": [
      15
    ],
    "85899072": [
      2
    ],
    "91486578": [
      2
    ],
    "96695514": [
      15
    ],
    "4566e668": [
      2
    ],
    "45262fe4": [
      2
    ],
    "7878060a": [
      2
    ],
    "bd8954b2": [
      8
    ],
    "5be7832e": [
      2
    ],
    "5e90fc2a": [
      2
    ],
    "3f80e754": [
      8
    ],
    "c4ef7494": [
      8
    ],
    "80f96fa0": [
      8
    ],
    "a3bd28ba": [
      8
    ],
    "bc2fa568": [
      8
    ],
    "40cfc92a": [
      2
    ],
    "dbd20af2": [
      2
    ],
    "4e63db97": [
      2
    ],
    "70eaac24": [
      2
    ],
    "82880c60": [
      2
    ],
    "61d49ffc": [
      2
    ],
    "531b6d0a": [
      15
    ],
    "2797a253": [
      8
    ],
    "f1bc7380": [
      2
    ],
    "ea7ce270": [
      2
    ],
    "6925ebe6": [
      2
    ],
    "6ff4d55f": [
      2
    ],
    "1d9a838a": [
      2
    ],
    "066b8994": [
      2
    ],
    "4a6447ad": [
      8
    ],
    "81b2843a": [
      8
    ],
    "5e41844b": [
      2
    ],
    "710438c9": [
      8
    ],
    "41e7825c": [
      2
    ],
    "355c5184": [
      8
    ],
    "1dd0afce": [
      8
    ],
    "48569d5e": [
      8
    ],
    "e4eb564c": [
      2
    ],
    "09aa72e4": [
      8
    ],
    "5cc7241a": [
      8
    ],
    "7a677aa7": [
      2
    ],
    "6d598257": [
      2
    ],
    "212f6f4b": [
      8
    ],
    "38220e2e": [
      8
    ],
    "223842b7": [
      2
    ],
    "0ea5af0e": [
      2
    ],
    "a018a474": [
      2
    ],
    "05526860": [
      2
    ],
    "40f1b385": [
      8
    ],
    "3063f4d0": [
      8
    ],
    "ac9d0ace": [
      8
    ],
    "1f4d209a": [
      8
    ],
    "766905f2": [
      8
    ],
    "248c58f3": [
      8
    ],
    "3894adf6": [
      2
    ],
    "d6512342": [
      2
    ],
    "49ee7a28": [
      2
    ],
    "2364c233": [
      2
    ],
    "93a2fd82": [
      8
    ],
    "30b7c8bb": [
      8
    ],
    "7501b255": [
      8
    ],
    "a6c28c3c": [
      2
    ],
    "f6ecd270": [
      2
    ],
    "086b2bba": [
      2
    ],
    "3f020b60": [
      8
    ],
    "487eac6c": [
      8
    ],
    "745bb785": [
      8
    ],
    "8df27ab8": [
      8
    ],
    "41e2a2c3": [
      8
    ],
    "448727eb": [
      2
    ],
    "1dd65cd6": [
      2
    ],
    "2709263a": [
      2
    ],
    "157f9d90": [
      2
    ],
    "6b13115a": [
      8
    ],
    "fdb3db3c": [
      8
    ],
    "7ea2dddf": [
      8
    ],
    "03ab1373": [
      8
    ],
    "079e4674": [
      8
    ],
    "812e08ea": [
      8
    ],
    "223ebf5c": [
      8
    ],
    "bfdc9f5a": [
      2
    ],
    "f9970c1c": [
      2
    ],
    "04fffc83": [
      2
    ],
    "1137c1d2": [
      2
    ],
    "ca90893c": [
      15
    ],
    "b932b96a": [
      8
    ],
    "083b8eda": [
      8
    ],
    "0b3aff23": [
      2
    ],
    "294f30da": [
      2
    ],
    "dabfd5fa": [
      2
    ],
    "d6ee8b56": [
      2
    ],
    "4bad9c07": [
      2
    ],
    "05ffa648": [
      2
    ],
    "7440c70f": [
      2
    ],
    "52c0c4e7": [
      2
    ],
    "2e3f5549": [
      15
    ],
    "582d5dac": [
      15
    ],
    "69d82e03": [
      15
    ],
    "1b576a4a": [
      15
    ],
    "5b38fdb2": [
      15
    ],
    "fd5f7a8c": [
      15
    ],
    "e437524c": [
      15
    ],
    "5d7b5332": [
      15
    ],
    "09471f25": [
      15
    ],
    "28ab41d8": [
      15
    ],
    "dc561098": [
      15
    ],
    "7d2ba962": [
      15
    ],
    "25e0ecb3": [
      15
    ],
    "188ae7d4": [
      15
    ],
    "8a0391ea": [
      15
    ],
    "822c2702": [
      15
    ],
    "87bde756": [
      15
    ],
    "8a10f7ac": [
      15
    ],
    "088bccd2": [
      15
    ],
    "0c76cd40": [
      15
    ],
    "650fcaec": [
      15
    ],
    "e803e6ce": [
      15
    ],
    "9408beee": [
      15
    ],
    "eec2c906": [
      15
    ],
    "5d64fb28": [
      15
    ],
    "8e4562f0": [
      15
    ],
    "7de90f37": [
      15
    ],
    "8333453c": [
      4
    ],
    "ba7fefa6": [
      8
    ],
    "024b8cdc": [
      2
    ],
    "81c0bf98": [
      2
    ],
    "5057a3ce": [
      2
    ],
    "8f0f1e4a": [
      2
    ],
    "7ce124f4": [
      2
    ],
    "21605c1a": [
      2
    ],
    "5c201329": [
      2
    ],
    "435b9671": [
      2
    ],
    "5b97ef88": [
      2
    ],
    "2df6e684": [
      8
    ],
    "ca45aebe": [
      2
    ],
    "7a80ddc9": [
      8
    ],
    "70171eb4": [
      2
    ],
    "73ff8375": [
      8
    ],
    "58edb29c": [
      8
    ],
    "29ffb8a4": [
      8
    ],
    "1a43fdfd": [
      8
    ],
    "c41a9830": [
      8
    ],
    "502d3930": [
      8
    ],
    "2f042823": [
      8
    ],
    "3f45d9ce": [
      8
    ],
    "5624ab68": [
      8
    ],
    "5382c8d0": [
      8
    ],
    "2ddeccee": [
      8
    ],
    "4288d77a": [
      2
    ],
    "ae5633fa": [
      2
    ],
    "1d462b37": [
      2
    ],
    "3fae6880": [
      2
    ],
    "1059f11b": [
      2
    ],
    "02f75f7e": [
      15
    ],
    "1f798c35": [
      8
    ],
    "359e644e": [
      2
    ],
    "c08838a0": [
      2
    ],
    "072407a8": [
      8
    ],
    "5a1bb548": [
      8
    ],
    "d3566ec6": [
      8
    ],
    "688bbd7a": [
      8
    ],
    "fda36b88": [
      8
    ],
    "3f414e18": [
      8
    ],
    "3f4ef13a": [
      8
    ],
    "7b2ac407": [
      8
    ],
    "356a4cc4": [
      8
    ],
    "5c9ad384": [
      8
    ],
    "1fc556e6": [
      8
    ],
    "8c4ba55e": [
      8
    ],
    "19c7b5f4": [
      8
    ],
    "7e1aa1e0": [
      2
    ],
    "1fabe3c1": [
      15
    ],
    "e87c4ddc": [
      15
    ],
    "7faa1e5e": [
      15
    ],
    "6f1510c9": [
      2
    ],
    "b2c22eb6": [
      2
    ],
    "1182aef0": [
      15
    ],
    "33081c03": [
      2
    ],
    "3160f69d": [
      2
    ],
    "4008a9fb": [
      2
    ],
    "0ac0c1a3": [
      2
    ],
    "ada2bf02": [
      2
    ],
    "60ca7027": [
      2
    ],
    "1d82dec7": [
      2
    ],
    "0d0a4836": [
      2
    ],
    "e1a19a1a": [
      2
    ],
    "9bbd9c00": [
      15
    ],
    "7c601b10": [
      2
    ],
    "9a3e363e": [
      2
    ],
    "f3944058": [
      8
    ],
    "c29d6108": [
      2
    ],
    "71bf163d": [
      8
    ],
    "4ba28d9a": [
      8
    ],
    "61d96136": [
      8
    ],
    "36adb2ec": [
      8
    ],
    "e41e2d98": [
      8
    ],
    "364b1f40": [
      8
    ],
    "cf637950": [
      8
    ],
    "7813ad41": [
      8
    ],
    "33b6f60d": [
      8
    ],
    "a5bfd010": [
      8
    ],
    "30ba1ca6": [
      8
    ],
    "25239a78": [
      8
    ],
    "c0e407c2": [
      8
    ],
    "86c1dc48": [
      8
    ],
    "4eeec055": [
      8
    ],
    "b1f492a0": [
      8
    ],
    "5ef7c7a9": [
      2
    ],
    "9fd1d42c": [
      8
    ],
    "0910edc3": [
      8
    ],
    "3ceb8c5a": [
      2
    ],
    "781efeea": [
      2
    ],
    "08702c9d": [
      2
    ],
    "edb35afa": [
      2
    ],
    "ce4288aa": [
      2
    ],
    "aba8c1ba": [
      2
    ],
    "2a35145e": [
      2
    ],
    "9bcff17a": [
      2
    ],
    "6b30f732": [
      2
    ],
    "51d74677": [
      2
    ],
    "17020c84": [
      2
    ],
    "0605f773": [
      2
    ],
    "45972f06": [
      8
    ],
    "1656e3f9": [
      8
    ],
    "8b69d8e4": [
      8
    ],
    "010557d6": [
      2
    ],
    "efb1cb32": [
      2
    ],
    "372d85b6": [
      15
    ],
    "205d5d18": [
      15
    ],
    "f9d109c2": [
      15
    ],
    "ce1ce476": [
      15
    ],
    "e95ce186": [
      15
    ],
    "05dcc07a": [
      15
    ],
    "02e95d76": [
      15
    ],
    "efa24240": [
      15
    ],
    "08f5c611": [
      15
    ],
    "955c4106": [
      15
    ],
    "42b8154e": [
      15
    ],
    "b35009b2": [
      15
    ],
    "633eb158": [
      15
    ],
    "7a16c8cd": [
      15
    ],
    "bcd6078e": [
      15
    ],
    "0b962cec": [
      15
    ],
    "1c87f094": [
      15
    ],
    "80f17600": [
      15
    ],
    "29a32b6c": [
      15
    ],
    "dc85a1b6": [
      15
    ],
    "375c1d0f": [
      15
    ],
    "38e984d7": [
      15
    ],
    "c3d76f2c": [
      15
    ],
    "7e44139c": [
      15
    ],
    "5205607e": [
      15
    ],
    "e4495956": [
      2
    ],
    "e18e197e": [
      2
    ],
    "3e263cc8": [
      2
    ],
    "d5e40a92": [
      2
    ],
    "9eb6bdbe": [
      15
    ],
    "ac29d312": [
      15
    ],
    "4b98cd1d": [
      15
    ],
    "461b49d4": [
      15
    ],
    "e2034482": [
      15
    ],
    "0705b9d8": [
      15
    ],
    "012ad0f4": [
      15
    ],
    "309cecba": [
      15
    ],
    "2d9b3f17": [
      15
    ],
    "5e685ec1": [
      15
    ],
    "7f462215": [
      15
    ],
    "416551fe": [
      8
    ],
    "699c2bec": [
      8
    ],
    "3c7c84f9": [
      8
    ],
    "db16a87c": [
      8
    ],
    "75bb5702": [
      8
    ],
    "dc2ba254": [
      8
    ],
    "240181d0": [
      8
    ],
    "26458cfa": [
      8
    ],
    "53c5fdab": [
      8
    ],
    "89b1c5e4": [
      8
    ],
    "5337930e": [
      8
    ],
    "22806ef6": [
      8
    ],
    "571f07cc": [
      8
    ],
    "2e9fda0c": [
      8
    ],
    "f023d044": [
      8
    ],
    "f3d15cd8": [
      8
    ],
    "26c60a88": [
      8
    ],
    "227f162a": [
      8
    ],
    "949d9d04": [
      8
    ],
    "77b6845a": [
      8
    ],
    "32968ad4": [
      8
    ],
    "3c0c52ea": [
      8
    ],
    "524d1fc0": [
      8
    ],
    "a5ed9a44": [
      8
    ],
    "f2db3062": [
      8
    ],
    "0c4933d8": [
      8
    ],
    "76f0c878": [
      8
    ],
    "6aadfdee": [
      2
    ],
    "d915a73c": [
      2
    ],
    "f2e52a6a": [
      2
    ],
    "a82a436a": [
      2
    ],
    "f60e9a8e": [
      2
    ],
    "cf3fde86": [
      2
    ],
    "cf34f59e": [
      2
    ],
    "e7fdb7cc": [
      2
    ],
    "e73b28f8": [
      2
    ],
    "e71d287a": [
      2
    ],
    "e716cb48": [
      2
    ],
    "e66db13c": [
      2
    ],
    "e645b094": [
      2
    ],
    "cf2dafae": [
      2
    ],
    "cf249842": [
      2
    ],
    "cf22c6c6": [
      2
    ],
    "cf1d5252": [
      2
    ],
    "cf1c6994": [
      2
    ],
    "cf1b80d6": [
      2
    ],
    "cf18c69c": [
      2
    ],
    "cf17ddde": [
      2
    ],
    "cf0c0c38": [
      2
    ],
    "cefbaedc": [
      2
    ],
    "cef8f4a2": [
      2
    ],
    "cef63a68": [
      2
    ],
    "ceefdd36": [
      2
    ],
    "ceec3a3e": [
      2
    ],
    "13c6a7ad": [
      2
    ],
    "13dd623b": [
      2
    ],
    "cedcc5a0": [
      2
    ],
    "cec9ae0a": [
      2
    ],
    "56e62c14": [
      2
    ],
    "57c05e34": [
      2
    ],
    "57d375ca": [
      2
    ],
    "580c482d": [
      2
    ],
    "5829d44c": [
      2
    ],
    "582d02e5": [
      2
    ],
    "5879d59c": [
      2
    ],
    "cec6f3d0": [
      2
    ],
    "cec350d8": [
      2
    ],
    "606712c2": [
      2
    ],
    "615873cf": [
      2
    ],
    "cec2681a": [
      2
    ],
    "cec17f5c": [
      2
    ],
    "ceb77f32": [
      2
    ],
    "ceb03942": [
      2
    ],
    "ceaac4ce": [
      2
    ],
    "cea80a94": [
      2
    ],
    "d964e0a6": [
      2
    ],
    "d95e8374": [
      2
    ],
    "cea1ad62": [
      2
    ],
    "ce9b5030": [
      2
    ],
    "ce9895f6": [
      2
    ],
    "ce915006": [
      2
    ],
    "4bfe706b": [
      2
    ],
    "ce892158": [
      2
    ],
    "ce7b7e36": [
      2
    ],
    "ce77db3e": [
      2
    ],
    "ce6fac90": [
      2
    ],
    "ce6cf256": [
      2
    ],
    "557664b8": [
      2
    ],
    "ce6037f2": [
      2
    ],
    "ce5294d0": [
      2
    ],
    "ce51ac12": [
      2
    ],
    "34c0bb65": [
      2
    ],
    "ce46c32a": [
      2
    ],
    "ce33ab94": [
      2
    ],
    "ce2a9428": [
      2
    ],
    "ce217cbc": [
      2
    ],
    "ce1fab40": [
      2
    ],
    "ce1ec282": [
      2
    ],
    "ce1dd9c4": [
      2
    ],
    "ce186550": [
      2
    ],
    "ce14c258": [
      2
    ],
    "ce0d7c68": [
      2
    ],
    "ce01aac2": [
      2
    ],
    "cdfd1f0c": [
      2
    ],
    "cdfb4d90": [
      2
    ],
    "cdee932c": [
      2
    ],
    "cdeaf034": [
      2
    ],
    "cde91eb8": [
      2
    ],
    "cde835fa": [
      2
    ],
    "cde6647e": [
      2
    ],
    "cde2c186": [
      2
    ],
    "cde1d8c8": [
      2
    ],
    "c0184e0e": [
      2
    ],
    "cde0f00a": [
      2
    ],
    "cddc6454": [
      2
    ],
    "cdd51e64": [
      2
    ],
    "cdd2642a": [
      2
    ],
    "cdcc06f8": [
      2
    ],
    "d63565cc": [
      2
    ],
    "cdca357c": [
      2
    ],
    "1f29d6eb": [
      2
    ],
    "cd93a8f4": [
      2
    ],
    "cd8c6304": [
      2
    ],
    "0bdf69b3": [
      2
    ],
    "cd5890b6": [
      2
    ],
    "cd531c42": [
      2
    ],
    "cd4661de": [
      2
    ],
    "cd457920": [
      2
    ],
    "cd41d628": [
      2
    ],
    "cd4004ac": [
      2
    ],
    "cd3f1bee": [
      2
    ],
    "cd3a9038": [
      2
    ],
    "cd39a77a": [
      2
    ],
    "ead4d1a4": [
      2
    ],
    "cd38bebc": [
      2
    ],
    "cd360482": [
      2
    ],
    "cd351bc4": [
      2
    ],
    "cd2ced16": [
      2
    ],
    "cd294a1e": [
      2
    ],
    "d7c2196e": [
      2
    ],
    "cd2778a2": [
      2
    ],
    "cd268fe4": [
      2
    ],
    "04f3007f": [
      2
    ],
    "d707b948": [
      2
    ],
    "cd1d7878": [
      2
    ],
    "d5798434": [
      2
    ],
    "d5789b76": [
      2
    ],
    "5ac3608d": [
      2
    ],
    "63a08dc6": [
      2
    ],
    "cd07a6a8": [
      2
    ],
    "cd014976": [
      2
    ],
    "ccfa0386": [
      2
    ],
    "6ee660d6": [
      2
    ],
    "cced4922": [
      2
    ],
    "0793012f": [
      2
    ],
    "cc9347a8": [
      2
    ],
    "c026ad3c": [
      2
    ],
    "bf9c7c6c": [
      2
    ],
    "be3f5f6c": [
      2
    ],
    "75323afa": [
      8
    ],
    "180956f8": [
      2
    ],
    "4838c9aa": [
      8
    ],
    "fbcda312": [
      8
    ],
    "2c909d93": [
      8
    ],
    "6ce8b01d": [
      8
    ],
    "164c96ce": [
      8
    ],
    "4bbcb17e": [
      8
    ],
    "64dc741c": [
      8
    ],
    "1d60f22e": [
      8
    ],
    "3c37c087": [
      8
    ],
    "e4341020": [
      15
    ],
    "0f4aa908": [
      15
    ],
    "7394b19c": [
      15
    ],
    "2419c4b6": [
      15
    ],
    "099b37d4": [
      15
    ],
    "18067c67": [
      15
    ],
    "1793ed72": [
      15
    ],
    "681df0d1": [
      15
    ],
    "f6b1c240": [
      15
    ],
    "6e26fffc": [
      15
    ],
    "f629e1fc": [
      15
    ],
    "60ddb63e": [
      15
    ],
    "e72299fa": [
      2
    ],
    "a77f5082": [
      2
    ],
    "0a80a683": [
      2
    ],
    "7251bb86": [
      2
    ],
    "6b9970f6": [
      8
    ],
    "789307e2": [
      2
    ],
    "7225563f": [
      2
    ],
    "e2e548a0": [
      2
    ],
    "757b593a": [
      8
    ],
    "98353e8e": [
      8
    ],
    "17a03cd7": [
      15
    ],
    "585f8d68": [
      15
    ],
    "4213939a": [
      8
    ],
    "3c9d0948": [
      8
    ],
    "1af30268": [
      8
    ],
    "200fbac9": [
      8
    ],
    "5a8dd08d": [
      8
    ],
    "3a0952c5": [
      8
    ],
    "b9ede8a0": [
      8
    ],
    "520ef64b": [
      8
    ],
    "6cb39f2e": [
      8
    ],
    "04c9c8e4": [
      8
    ],
    "6ec39a4c": [
      8
    ],
    "43c76ac8": [
      8
    ],
    "06c54f20": [
      8
    ],
    "4f07faf5": [
      8
    ],
    "b28040b4": [
      8
    ],
    "b69b7134": [
      8
    ],
    "d5e5a6da": [
      8
    ],
    "37d7edf0": [
      8
    ],
    "3c0d3552": [
      8
    ],
    "85c34a34": [
      8
    ],
    "194ab76c": [
      8
    ],
    "33441f46": [
      15
    ],
    "5a5b7ca9": [
      15
    ],
    "7ba20a49": [
      2
    ],
    "7a62a154": [
      2
    ],
    "71a841ae": [
      15
    ],
    "436cd9fa": [
      15
    ],
    "4c885a6d": [
      15
    ],
    "8757b08e": [
      15
    ],
    "6a45512f": [
      8
    ],
    "429ae2b5": [
      8
    ],
    "c402395e": [
      2
    ],
    "c0d273c8": [
      2
    ],
    "5c73e06e": [
      2
    ],
    "7e03ad58": [
      2
    ],
    "5f811599": [
      8
    ],
    "2d961d09": [
      2
    ],
    "2c56b414": [
      2
    ],
    "243b24cd": [
      2
    ],
    "c9d5e6d0": [
      2
    ],
    "d19aad2e": [
      2
    ],
    "d4197f18": [
      2
    ],
    "828fa2a2": [
      8
    ],
    "6a8de7f2": [
      2
    ],
    "7af7b848": [
      2
    ],
    "54cdfb46": [
      2
    ],
    "2bb691a8": [
      2
    ],
    "62e12a20": [
      8
    ],
    "02558438": [
      8
    ],
    "1b7f7f43": [
      2
    ],
    "6c767f8e": [
      2
    ],
    "61dcbbaa": [
      2
    ],
    "a0227018": [
      2
    ],
    "1a0b6ec9": [
      2
    ],
    "1535cad4": [
      2
    ],
    "6664ccf9": [
      2
    ],
    "a49c61b4": [
      2
    ],
    "a16c9c1e": [
      2
    ],
    "1a455ee0": [
      2
    ],
    "4ba9d575": [
      2
    ],
    "3cb7267a": [
      2
    ],
    "398760e4": [
      2
    ],
    "1193b0d3": [
      2
    ],
    "7800d4e8": [
      2
    ],
    "6348f618": [
      2
    ],
    "bc11652a": [
      2
    ],
    "0fd64694": [
      2
    ],
    "b9028e2e": [
      2
    ],
    "c2add618": [
      2
    ],
    "5efef2bd": [
      15
    ],
    "a7fa3132": [
      8
    ],
    "1f86c783": [
      8
    ],
    "31e05f94": [
      2
    ],
    "1368d786": [
      2
    ],
    "103911f0": [
      2
    ],
    "bab4dbae": [
      2
    ],
    "dc44a898": [
      2
    ],
    "2163e52e": [
      2
    ],
    "42f3b218": [
      2
    ],
    "176020c6": [
      2
    ],
    "bcea635e": [
      2
    ],
    "fc5c89c8": [
      2
    ],
    "bd06f12e": [
      2
    ],
    "c6b23918": [
      2
    ],
    "64b73f1d": [
      2
    ],
    "e6933fb0": [
      2
    ],
    "47b37ac9": [
      2
    ],
    "42ddd6d4": [
      2
    ],
    "6ff1a109": [
      2
    ],
    "51ae00d8": [
      2
    ],
    "35d0a99d": [
      2
    ],
    "f270ac30": [
      2
    ],
    "f43dfd12": [
      2
    ],
    "524ffc7c": [
      2
    ],
    "272e8280": [
      15
    ],
    "2f1d84c4": [
      8
    ],
    "172ec0b2": [
      15
    ],
    "b5a4762e": [
      2
    ],
    "0c652374": [
      2
    ],
    "c36fa0c6": [
      2
    ],
    "501b6874": [
      2
    ],
    "3c555d5b": [
      2
    ],
    "968994ce": [
      2
    ],
    "9359cf38": [
      2
    ],
    "007d87a3": [
      2
    ],
    "7323c6b8": [
      2
    ],
    "737cc330": [
      2
    ],
    "559e66bb": [
      2
    ],
    "6711681e": [
      8
    ],
    "03e98aaa": [
      8
    ],
    "1084e7ed": [
      2
    ],
    "f9a9b1fc": [
      2
    ],
    "6afa8550": [
      8
    ],
    "1ee0c70a": [
      8
    ],
    "146de8e5": [
      2
    ],
    "f1d7b00c": [
      2
    ],
    "43647a8c": [
      15
    ],
    "23e091d8": [
      15
    ],
    "3e8620e0": [
      15
    ],
    "4ec4bb8e": [
      15
    ],
    "9d84be5c": [
      15
    ],
    "48b07adf": [
      15
    ],
    "582e436b": [
      2
    ],
    "6a56fb00": [
      2
    ],
    "a4fb493e": [
      2
    ],
    "20289a76": [
      2
    ],
    "52f467ef": [
      2
    ],
    "2ad96844": [
      2
    ],
    "2c6ae466": [
      2
    ],
    "293b1ed0": [
      2
    ],
    "3f1a7046": [
      2
    ],
    "5bbe9e4a": [
      2
    ],
    "526fe994": [
      8
    ],
    "a14debc2": [
      8
    ],
    "2c94b80d": [
      8
    ],
    "18f1d18a": [
      8
    ],
    "2828b6b2": [
      8
    ],
    "51e791de": [
      8
    ],
    "913d6e9a": [
      8
    ],
    "651ee65c": [
      8
    ],
    "6ab7ba1b": [
      8
    ],
    "139705cc": [
      8
    ],
    "7bcb0ebe": [
      8
    ],
    "79ac3d2e": [
      8
    ],
    "5cdf320b": [
      8
    ],
    "3e39050c": [
      8
    ],
    "912d9052": [
      8
    ],
    "79f4ee24": [
      8
    ],
    "2f586b7e": [
      8
    ],
    "35a28508": [
      8
    ],
    "0c622ad2": [
      2
    ],
    "6ffa1b16": [
      2
    ],
    "62873f3a": [
      2
    ],
    "7e155519": [
      2
    ],
    "aab075fa": [
      2
    ],
    "6966fee3": [
      2
    ],
    "e884b5b2": [
      2
    ],
    "a0d504f8": [
      2
    ],
    "7e815463": [
      2
    ],
    "c1903c76": [
      2
    ],
    "1e0bed5d": [
      2
    ],
    "2fa98af0": [
      2
    ],
    "02819287": [
      2
    ],
    "04ed599f": [
      2
    ],
    "ee0ae2b6": [
      2
    ],
    "bacf7fea": [
      2
    ],
    "3a3e2bd7": [
      2
    ],
    "2da9f2cc": [
      2
    ],
    "023bd65e": [
      2
    ],
    "bf7650e0": [
      2
    ],
    "6d72b25e": [
      2
    ],
    "e593db72": [
      2
    ],
    "eab9e39a": [
      2
    ],
    "a718f710": [
      2
    ],
    "5a589459": [
      2
    ],
    "7ecee739": [
      2
    ],
    "16fd3538": [
      2
    ],
    "00da050c": [
      2
    ],
    "184731cb": [
      2
    ],
    "ddcb55c8": [
      2
    ],
    "562344a2": [
      2
    ],
    "c6246d6c": [
      2
    ],
    "dd5e1026": [
      2
    ],
    "5d60c78e": [
      2
    ],
    "14358cbc": [
      2
    ],
    "46c54f45": [
      2
    ],
    "6c87d650": [
      2
    ],
    "2bb6bf76": [
      2
    ],
    "4b3b1f4f": [
      2
    ],
    "2b52bdd2": [
      2
    ],
    "3f06d4c8": [
      2
    ],
    "106b95f6": [
      2
    ],
    "5997e934": [
      2
    ],
    "d92c409c": [
      2
    ],
    "d63823cc": [
      2
    ],
    "4c67ee93": [
      2
    ],
    "1e2a4d52": [
      2
    ],
    "628692ce": [
      2
    ],
    "7e902a42": [
      2
    ],
    "4f1c7f5e": [
      2
    ],
    "ef65589e": [
      2
    ],
    "e7c25528": [
      2
    ],
    "a07d760a": [
      2
    ],
    "7bd1f6ec": [
      2
    ],
    "072f1cab": [
      2
    ],
    "621ec9b4": [
      2
    ],
    "17bac1d7": [
      2
    ],
    "9dd8be42": [
      2
    ],
    "37f11fec": [
      2
    ],
    "307a3177": [
      2
    ],
    "ed05ac6e": [
      2
    ],
    "76612abe": [
      2
    ],
    "01b88dcf": [
      2
    ],
    "0755fc81": [
      2
    ],
    "44631c62": [
      2
    ],
    "dbb4d7e2": [
      2
    ],
    "70df0827": [
      2
    ],
    "3b001c02": [
      2
    ],
    "07c1054b": [
      2
    ],
    "46ed87d9": [
      2
    ],
    "14164c1d": [
      2
    ],
    "785ea2b2": [
      2
    ],
    "3a72eeab": [
      2
    ],
    "014e9b4c": [
      2
    ],
    "26d27bce": [
      2
    ],
    "044189fa": [
      2
    ],
    "193b861e": [
      2
    ],
    "fe2cb1b2": [
      4
    ],
    "63b69a42": [
      4
    ],
    "01e907cc": [
      6
    ],
    "61e02ea5": [
      1
    ],
    "4e2da569": [
      1
    ],
    "9535f818": [
      1
    ],
    "78ffbb10": [
      1
    ],
    "290178fa": [
      1
    ],
    "468085c8": [
      1
    ],
    "017ac767": [
      1
    ],
    "145ce3a9": [
      4
    ],
    "7b944234": [
      4
    ],
    "49a389b6": [
      6
    ],
    "e0b969fc": [
      6
    ],
    "499394a9": [
      16
    ],
    "7192b5b4": [
      16
    ],
    "603b5336": [
      16
    ],
    "16c53ea0": [
      16
    ],
    "76ff0784": [
      16
    ],
    "c77dadce": [
      16
    ],
    "131b10e4": [
      16
    ],
    "402a6b55": [
      16
    ],
    "41c24e20": [
      16
    ],
    "2a8182ab": [
      3
    ],
    "048507f6": [
      3
    ],
    "3906c5bb": [
      16
    ],
    "3328a7af": [
      16
    ],
    "d1d20202": [
      1
    ],
    "47c709c3": [
      4
    ],
    "28090ca8": [
      16
    ],
    "34e02368": [
      11
    ],
    "3cbb33c4": [
      11
    ],
    "510a1e2c": [
      11
    ],
    "124fc77c": [
      11
    ],
    "508659e8": [
      11
    ],
    "62b50727": [
      11
    ],
    "62a6efa6": [
      11
    ],
    "e987c3f4": [
      11
    ],
    "25ffe70b": [
      11
    ],
    "270f8ef5": [
      11
    ],
    "7e519970": [
      11
    ],
    "0f42cdf5": [
      11
    ],
    "42bc56f7": [
      11
    ],
    "ff5706ce": [
      11
    ],
    "5d3e7f32": [
      11
    ],
    "c69287ae": [
      11
    ],
    "78ba71f3": [
      11
    ],
    "f2e8a4e4": [
      11
    ],
    "b0edd6d8": [
      11
    ],
    "177ce213": [
      11
    ],
    "b2472e16": [
      11
    ],
    "66bf2abb": [
      11
    ],
    "e2b3d6ae": [
      11
    ],
    "7ff08f94": [
      11
    ],
    "666ea1cd": [
      11
    ],
    "0f3302ee": [
      11
    ],
    "1ae991cf": [
      11
    ],
    "17ab2ff3": [
      11
    ],
    "40ac7923": [
      11
    ],
    "495524c9": [
      11
    ],
    "69f8fcc1": [
      11
    ],
    "61ad9e47": [
      11
    ],
    "845116b6": [
      6
    ],
    "161ad0b2": [
      6
    ],
    "8b0acab0": [
      6
    ],
    "551c6c6e": [
      6
    ],
    "5324b2ea": [
      6
    ],
    "0ec1fcaa": [
      6
    ],
    "02c209fa": [
      6
    ],
    "2a1a5043": [
      6
    ],
    "01ca799c": [
      6
    ],
    "49fc7e05": [
      6
    ],
    "79225ee0": [
      6
    ],
    "ee03fb7c": [
      6
    ],
    "1d64051d": [
      6
    ],
    "ed7c1b38": [
      6
    ],
    "101abb5f": [
      6
    ],
    "2040591a": [
      6
    ],
    "562c4806": [
      6
    ],
    "f7927c38": [
      6
    ],
    "40e64bca": [
      6
    ],
    "06f4461b": [
      6
    ],
    "80605f60": [
      6
    ],
    "6b21d802": [
      6
    ],
    "2c4b7fc8": [
      6
    ],
    "671814bd": [
      6
    ],
    "b8fd65dc": [
      6
    ],
    "3302ae6b": [
      6
    ],
    "34b94880": [
      6
    ],
    "f3daec5c": [
      6
    ],
    "16becd1e": [
      6
    ],
    "634588fa": [
      1
    ],
    "144a0e94": [
      1
    ],
    "22fa048a": [
      1
    ],
    "67ddf8d2": [
      1
    ],
    "0559139f": [
      1
    ],
    "b52d9f44": [
      1
    ],
    "4cb257f8": [
      1
    ],
    "fdbc3d18": [
      1
    ],
    "c02b8648": [
      1
    ],
    "246e1c63": [
      1
    ],
    "a6193768": [
      1
    ],
    "93b6c9b6": [
      1
    ],
    "1ea34834": [
      1
    ],
    "0b223fa0": [
      3
    ],
    "d9395650": [
      3
    ],
    "6731723d": [
      3
    ],
    "7ca249bb": [
      3
    ],
    "ac6375f6": [
      3
    ],
    "06322a19": [
      7
    ],
    "f4838aea": [
      7
    ],
    "4df8cbe4": [
      7
    ],
    "95b566ae": [
      7
    ],
    "6adc883c": [
      7
    ],
    "66b01e6c": [
      5
    ],
    "e1d0583a": [
      5
    ],
    "1c71aec1": [
      5
    ],
    "6f970605": [
      5
    ],
    "95c871fa": [
      5
    ],
    "566c3a92": [
      9
    ],
    "71ef8f22": [
      9
    ],
    "fc44b1f4": [
      9
    ],
    "059090c0": [
      9
    ],
    "d16302f8": [
      9
    ],
    "3d354ff4": [
      13
    ],
    "674a2108": [
      13
    ],
    "793d9067": [
      13
    ],
    "f65918ac": [
      13
    ],
    "da965dae": [
      13
    ],
    "24bb1808": [
      10
    ],
    "49bdfac0": [
      10
    ],
    "23ad9d61": [
      10
    ],
    "391e74df": [
      10
    ],
    "4d91f7da": [
      16
    ],
    "370aee72": [
      16
    ],
    "12dd1773": [
      16
    ],
    "aa3504f0": [
      16
    ],
    "084b797a": [
      16
    ],
    "1b63fc4b": [
      16
    ],
    "d3955f82": [
      16
    ],
    "52a82c15": [
      16
    ],
    "3ee4eb9c": [
      16
    ]
  },
  "assetsMapping": {
    "11a654f520784684b6aa.js": "44155356",
    "17e699498305c7ff6df5.js": "7ea1d828",
    "26d5db59123458392e2c.js": "3cdf16e1",
    "3815ef41efb6895f3788.js": "24ac4c92",
    "433211e6c71f28873e71.js": "6e756b1b",
    "487b94672ebf506a4b2d.js": "69aac5d4",
    "51270e3b36c76d4e5a07.js": "ffd1d8cc",
    "64d07703f4267d1456dd.js": "0859c165",
    "659121f4f3bec0c1b84a.js": "3d09dd78",
    "8ac408db1f8de67c8087.js": "3c7fd93d",
    "97646f7ee231e3480e82.js": "764e977a",
    "b60edd0b7a1f0544497c.js": "b1b3b116",
    "c7382fcef0a74136ba08.js": "6fca0322",
    "da0de3a983393419fc24.js": "1a3ae26b",
    "e9235617c50fe3499061.js": "3b7ff4b7"
  }
}